huntflow_api_client-3.0.108.dist-info/METADATA
huntflow_api_client-3.0.108.dist-info/WHEEL
huntflow_api_client-3.0.108.dist-info/licenses/LICENSE
huntflow_api_client/__init__.py
huntflow_api_client/api.py
huntflow_api_client/entities/__init__.py
huntflow_api_client/entities/account_offers.py
huntflow_api_client/entities/account_vacancy_request.py
huntflow_api_client/entities/accounts.py
huntflow_api_client/entities/action_logs.py
huntflow_api_client/entities/applicant_logs.py
huntflow_api_client/entities/applicant_offers.py
huntflow_api_client/entities/applicant_on_vacancy.py
huntflow_api_client/entities/applicant_on_vacancy_status.py
huntflow_api_client/entities/applicants.py
huntflow_api_client/entities/base.py
huntflow_api_client/entities/coworkers.py
huntflow_api_client/entities/delayed_tasks.py
huntflow_api_client/entities/dictionaries.py
huntflow_api_client/entities/divisions.py
huntflow_api_client/entities/email_templates.py
huntflow_api_client/entities/file.py
huntflow_api_client/entities/multi_vacancies.py
huntflow_api_client/entities/organization_settings.py
huntflow_api_client/entities/production_calendars.py
huntflow_api_client/entities/questionary.py
huntflow_api_client/entities/regions.py
huntflow_api_client/entities/rejection_reason.py
huntflow_api_client/entities/resume.py
huntflow_api_client/entities/survey_type_q.py
huntflow_api_client/entities/tags.py
huntflow_api_client/entities/user_settings.py
huntflow_api_client/entities/users.py
huntflow_api_client/entities/users_management.py
huntflow_api_client/entities/vacancies.py
huntflow_api_client/entities/vacancy_requests.py
huntflow_api_client/entities/webhooks.py
huntflow_api_client/errors/__init__.py
huntflow_api_client/errors/errors.py
huntflow_api_client/errors/handlers.py
huntflow_api_client/errors/response_hooks.py
huntflow_api_client/models/__init__.py
huntflow_api_client/models/common.py
huntflow_api_client/models/consts.py
huntflow_api_client/models/request/__init__.py
huntflow_api_client/models/request/applicant_logs.py
huntflow_api_client/models/request/applicant_offers.py
huntflow_api_client/models/request/applicant_on_vacancy.py
huntflow_api_client-3.0.108.dist-info/RECORD
