Metadata-Version: 2.1
Name: huntflow-api-client
Version: 3.0.108
Summary: Huntflow API Client for Python
Author-Email: Developers huntflow <developer@huntflow.ru>
License: MIT
Classifier: Programming Language :: Python :: 3
Classifier: Programming Language :: Python :: 3.8
Classifier: Programming Language :: Python :: 3.9
Classifier: Programming Language :: Python :: 3.10
Classifier: Programming Language :: Python :: 3.11
Requires-Python: >3.8
Requires-Dist: httpx>=0.23.3
Requires-Dist: email-validator>=1.3.1
Requires-Dist: pydantic>=2.3.0
